{"is_source_file": true, "format": "Dart", "description": "This file defines the CartScreen widget for a Flutter app, displaying shopping cart contents, allowing item quantity adjustments, and placing orders.", "external_files": ["package:flutter/material.dart", "package:provider/provider.dart", "package:restaurant_frontend/src/app_theme.dart", "package:restaurant_frontend/src/providers/cart_provider.dart", "package:restaurant_frontend/src/providers/orders_provider.dart", "package:restaurant_frontend/src/widgets/glass.dart"], "external_methods": ["context.watch<CartProvider>()", "context.read<OrdersProvider>()", "cart.decrease()", "cart.add()", "cart.remove()", "cart.clear()", "orders.placeOrder()", "showDialog()"], "published": ["CartScreen"], "classes": [{"name": "CartScreen", "description": "StatelessWidget that displays the shopping cart, order summary, and place order button.", "methods": [{"name": "build", "description": "Builds the widget tree for the cart screen."}]}, {"name": "_QtyControl", "description": "Widget managing quantity controls for cart items.", "methods": [{"name": "build", "description": "Builds the quantity control row with increment, decrement, and delete buttons."}]}, {"name": "_ScaleIconButton", "description": "A button with scale animation for tap effect.", "methods": [{"name": "build", "description": "Builds animated IconButton with tap scale effect."}]}, {"name": "_SummaryRow", "description": "Widget displaying a label and value for order summary.", "methods": [{"name": "build", "description": "Builds a row with label and formatted value."}]}, {"name": "_EmptyCart", "description": "Widget displayed when the cart is empty.", "methods": [{"name": "build", "description": "Builds UI showing empty cart message."}]}], "methods": [], "calls": ["context.watch<CartProvider>()", "context.read<OrdersProvider>()", "cart.decrease(line.item)", "cart.add(line.item)", "cart.remove(line.item)", "cart.clear()", "orders.placeOrder()", "showDialog()", "Navigator.of(ctx).pop()"], "search-terms": ["CartScreen", "Flutter cart page", "Order placement dialog", "Cart item widget", "Cart subtotal", "Empty cart", "GlassContainer"], "state": 2, "file_id": 28, "knowledge_revision": 89, "git_revision": "", "revision_history": [{"61": ""}, {"71": ""}, {"89": ""}], "hash": "10865be3c1f27427778b765910f357cd", "format-version": 4, "code-base-name": "restaurant_frontend", "filename": "restaurant_frontend/lib/src/screens/tabs/cart_screen.dart"}